{
  "log": {
    "version": "1.2",
    "creator": {
      "name": "WebInspector",
      "version": "537.36"
    },
    "pages": [
      {
        "startedDateTime": "2025-01-20T07:03:31.002Z",
        "id": "page_1",
        "title": "https://qa.gorollick.com/r/thank-you?trim=40015722&id=06fb27b1-2a01-4bb3-be29-d71fd7cadcbf&dids=25de28ce5975c939",
        "pageTimings": {
          "onContentLoad": 3148.486000020057,
          "onLoad": 15987.437000032514
        }
      }
    ],
    "entries": [
      {
        "_initiator": {
          "type": "script",
          "stack": {
            "callFrames": [
              {
                "functionName": "send",
                "scriptId": "891",
                "url": "https://qa.gorollick.com/scripts/jquery-3.6.1.min.js",
                "lineNumber": 1,
                "columnNumber": 82857
              },
              {
                "functionName": "ajax",
                "scriptId": "891",
                "url": "https://qa.gorollick.com/scripts/jquery-3.6.1.min.js",
                "lineNumber": 1,
                "columnNumber": 78434
              },
              {
                "functionName": "",
                "scriptId": "891",
                "url": "https://qa.gorollick.com/scripts/jquery-3.6.1.min.js",
                "lineNumber": 1,
                "columnNumber": 80487
              },
              {
                "functionName": "getLocationFromZip",
                "scriptId": "894",
                "url": "https://qa.gorollick.com/scripts/gorollick/common.js?2.186.0",
                "lineNumber": 293,
                "columnNumber": 25
              },
              {
                "functionName": "getLocationDetails",
                "scriptId": "984",
                "url": "https://qa.gorollick.com/scripts/gorollick/contact-us.js?2.186.0",
                "lineNumber": 140,
                "columnNumber": 14
              }
            ],
            "parent": {
              "description": "await",
              "callFrames": [
                {
                  "functionName": "init",
                  "scriptId": "984",
                  "url": "https://qa.gorollick.com/scripts/gorollick/contact-us.js?2.186.0",
                  "lineNumber": 25,
                  "columnNumber": 4
                },
                {
                  "functionName": "",
                  "scriptId": "984",
                  "url": "https://qa.gorollick.com/scripts/gorollick/contact-us.js?2.186.0",
                  "lineNumber": 153,
                  "columnNumber": 0
                }
              ]
            }
          }
        },
        "_priority": "High",
        "_resourceType": "xhr",
        "cache": {},
        "connection": "5519298",
        "pageref": "page_1",
        "request": {
          "method": "GET",
          "url": "https://qa.gorollick.com/api/geocode/86336",
          "httpVersion": "http/2.0",
          "headers": [
            {
              "name": ":authority",
              "value": "qa.gorollick.com"
            },
            {
              "name": ":method",
              "value": "GET"
            },
            {
              "name": ":path",
              "value": "/api/geocode/86336"
            },
            {
              "name": ":scheme",
              "value": "https"
            },
            {
              "name": "accept",
              "value": "*/*"
            },
            {
              "name": "accept-encoding",
              "value": "gzip, deflate, br, zstd"
            },
            {
              "name": "accept-language",
              "value": "en-US,en-IN;q=0.9,en;q=0.8,te;q=0.7"
            },
            {
              "name": "dnt",
              "value": "1"
            },
            {
              "name": "priority",
              "value": "u=1, i"
            },
            {
              "name": "referer",
              "value": "https://qa.gorollick.com/r/thank-you?trim=40015722&id=06fb27b1-2a01-4bb3-be29-d71fd7cadcbf&dids=25de28ce5975c939"
            },
            {
              "name": "sec-ch-ua",
              "value": "\"Google Chrome\";v=\"131\", \"Chromium\";v=\"131\", \"Not_A Brand\";v=\"24\""
            },
            {
              "name": "sec-ch-ua-mobile",
              "value": "?0"
            },
            {
              "name": "sec-ch-ua-platform",
              "value": "\"Windows\""
            },
            {
              "name": "sec-fetch-dest",
              "value": "empty"
            },
            {
              "name": "sec-fetch-mode",
              "value": "cors"
            },
            {
              "name": "sec-fetch-site",
              "value": "same-origin"
            },
            {
              "name": "user-agent",
              "value": "Mozilla/5.0 (Windows NT 10.0; Win64; x64) AppleWebKit/537.36 (KHTML, like Gecko) Chrome/131.0.0.0 Safari/537.36"
            },
            {
              "name": "x-requested-with",
              "value": "XMLHttpRequest"
            }
          ],
          "queryString": [],
          "cookies": [],
          "headersSize": -1,
          "bodySize": 0
        },
        "response": {
          "status": 200,
          "statusText": "",
          "httpVersion": "http/2.0",
          "headers": [
            {
              "name": "access-control-allow-credentials",
              "value": "true"
            },
            {
              "name": "access-control-allow-headers",
              "value": "Origin, X-Requested-With, Content-Type, Accept, Authorization"
            },
            {
              "name": "access-control-allow-methods",
              "value": "GET, OPTIONS"
            },
            {
              "name": "access-control-allow-origin",
              "value": "*"
            },
            {
              "name": "cache-control",
              "value": "private, no-cache, no-store, must-revalidate"
            },
            {
              "name": "cache-control",
              "value": "no-cache, must-revalidate"
            },
            {
              "name": "content-encoding",
              "value": "gzip"
            },
            {
              "name": "content-type",
              "value": "application/json; charset=utf-8"
            },
            {
              "name": "date",
              "value": "Mon, 20 Jan 2025 07:03:36 GMT"
            },
            {
              "name": "etag",
              "value": "W/\"318-TUn+Q69a69KhHVn6vAfg0k7hM1k\""
            },
            {
              "name": "server",
              "value": "nginx"
            },
            {
              "name": "strict-transport-security",
              "value": "max-age=15768000; includeSubDomains"
            },
            {
              "name": "vary",
              "value": "Accept-Encoding"
            }
          ],
          "cookies": [],
          "content": {
            "size": 792,
            "mimeType": "application/json"
          },
          "redirectURL": "",
          "headersSize": -1,
          "bodySize": -1,
          "_transferSize": 793,
          "_error": null,
          "_fetchedViaServiceWorker": false
        },
        "serverIPAddress": "52.162.210.125",
        "startedDateTime": "2025-01-20T07:03:33.866Z",
        "time": 356.9820001721382,
        "timings": {
          "blocked": 97.15500014060736,
          "dns": -1,
          "ssl": -1,
          "connect": -1,
          "send": 0.9849999999999994,
          "wait": 225.7800002039075,
          "receive": 33.06199982762337,
          "_blocked_queueing": 34.05100014060736,
          "_workerStart": -1,
          "_workerReady": -1,
          "_workerFetchStart": -1,
          "_workerRespondWithSettled": -1
        }
      }
    ]
  }
}